synheart_emotion/__init__.py
synheart_emotion/config.py
synheart_emotion/engine.py
synheart_emotion/error.py
synheart_emotion/features.py
synheart_emotion/models.py
synheart_emotion/result.py
synheart_emotion/data/extratrees_wrist_all_v1_0.meta.json
synheart_emotion/data/wesad_emotion_v1_0.json
synheart_emotion-0.0.1.dist-info/licenses/LICENSE
synheart_emotion-0.0.1.dist-info/METADATA
synheart_emotion-0.0.1.dist-info/WHEEL
synheart_emotion-0.0.1.dist-info/top_level.txt
synheart_emotion-0.0.1.dist-info/RECORD
