Metadata-Version: 2.4
Name: synheart-emotion
Version: 0.0.1
Summary: On-device emotion inference from biosignals (heart rate and RR intervals)
Author-email: Israel Goytom <opensource@synheart.ai>
License: MIT
Project-URL: Homepage, https://github.com/synheart-ai/synheart-emotion-python
Project-URL: Documentation, https://github.com/synheart-ai/synheart-emotion/tree/main/docs
Project-URL: Repository, https://github.com/synheart-ai/synheart-emotion-python
Project-URL: Issues, https://github.com/synheart-ai/synheart-emotion-python/issues
Keywords: emotion,biosignals,hrv,heart-rate,machine-learning,healthcare
Classifier: Development Status :: 3 - Alpha
Classifier: Intended Audience :: Developers
Classifier: Intended Audience :: Healthcare Industry
Classifier: Intended Audience :: Science/Research
Classifier: License :: OSI Approved :: MIT License
Classifier: Programming Language :: Python :: 3
Classifier: Programming Language :: Python :: 3.8
Classifier: Programming Language :: Python :: 3.9
Classifier: Programming Language :: Python :: 3.10
Classifier: Programming Language :: Python :: 3.11
Classifier: Programming Language :: Python :: 3.12
Classifier: Topic :: Scientific/Engineering :: Medical Science Apps.
Classifier: Topic :: Scientific/Engineering :: Artificial Intelligence
Requires-Python: >=3.8
License-File: LICENSE
Requires-Dist: numpy>=1.21.0
Requires-Dist: pandas>=1.3.0
Provides-Extra: ml
Requires-Dist: scikit-learn>=1.0.0; extra == "ml"
Requires-Dist: joblib>=1.1.0; extra == "ml"
Requires-Dist: xgboost>=1.5.0; extra == "ml"
Provides-Extra: dev
Requires-Dist: pytest>=7.0.0; extra == "dev"
Requires-Dist: pytest-cov>=3.0.0; extra == "dev"
Requires-Dist: black>=22.0.0; extra == "dev"
Requires-Dist: isort>=5.10.0; extra == "dev"
Requires-Dist: mypy>=0.950; extra == "dev"
Provides-Extra: all
Requires-Dist: synheart-emotion[dev,ml]; extra == "all"
Dynamic: license-file
